{"type": "Feature", "properties": {"Sección": 123, "DEL_ROM": "IV", "Tipo": "Urbana", "DEF": 2, "DEL": 4, "Municipio ID": 25, "Municipio": "Magdalena", "Lista Nominal": 2179, "Casillas": [{"presidente": "MIGUEL BURRUEL SINOGUI", "secretario1": "ELSA ISAMAR GARCIA ACUÑA", "secretario2": "STEPHANY PAOLA CAMACHO ENRIQUEZ", "escrutador1": "LUIS RODRIGO MENDOZA YANEZ", "escrutador2": "GRISEL PAOLA LOPEZ MEDRANO", "escrutador3": "RAMON BUSTAMANTE OCHOA", "suplente1": "MARIA ALEJANDRA IBAÑEZ GARDUÑO", "suplente2": "FRANCISCO ARTURO MORENO GONZALEZ", "suplente3": "JESUS GUADALUPE EGURROLA CASTRO", "direccion": "CENTRO DE ATENCIÓN MULTIPLE, CALLE AGUSTÍN DE ITURBIDE ENTRE SANTIAGO IGLESIAS Y ANTONIA GARCÍA COLONIA LOMAS DE KINO CÓDIGO POSTAL 84160 MAGDALENA DE KINO SONORA, FRENTE A LA SUBESTACIÓN DE LA COMISIÓN FEDERAL DE ELECTRICIDAD", "pos": [30.625035127784, -110.95232833203], "tipo": "Básica 01"}, {"presidente": "MARIA ADILENE GONZALEZ TREVIZO", "secretario1": "JAVIER FRANCISCO RAFAEL MARTINEZ REYES", "secretario2": "SUSET ARLETH HERNANDEZ LOVIO", "escrutador1": "YAZMIN ALEJANDRA CARDENAS BARRERAS", "escrutador2": "RAYMUNDO ALVARADO PIÑA", "escrutador3": "DANIRA JAQUELINE CAREAGA LUNA", "suplente1": "MARIA CONCEPCION LEON COTA", "suplente2": "ANA KARINA MENDIVIL VERA", "suplente3": "ZAIRA JAZANI LEYVA CORDOVA", "direccion": "CENTRO DE ATENCIÓN MULTIPLE, CALLE AGUSTÍN DE ITURBIDE ENTRE SANTIAGO IGLESIAS Y ANTONIA GARCÍA COLONIA LOMAS DE KINO CÓDIGO POSTAL 84160 MAGDALENA DE KINO SONORA, FRENTE A LA SUBESTACIÓN DE LA COMISIÓN FEDERAL DE ELECTRICIDAD", "pos": [30.625035127784, -110.95232833203], "tipo": "Contigua 01"}, {"presidente": "NUBIA ELIZABETH GORTAREZ ROBLES", "secretario1": "ALMA CRISTINA ALVAREZ TAPIA", "secretario2": "XOCHITL ESPERANZA DURAZO CHACON", "escrutador1": "OMAR ALEXIS GONZALEZ ESTRADA", "escrutador2": "CARLOS ARREDONDO GARCIA", "escrutador3": "ROSA MYRNA CARRILLO MAZON", "suplente1": "LUIS FRANCISCO LOPEZ MONTEVERDE", "suplente2": "RAMON ANDRADE MONTOYA", "suplente3": "FRANCISCA LOPEZ GARCIA", "direccion": "CENTRO DE ATENCIÓN MULTIPLE, CALLE AGUSTÍN DE ITURBIDE ENTRE SANTIAGO IGLESIAS Y ANTONIA GARCÍA COLONIA LOMAS DE KINO CÓDIGO POSTAL 84160 MAGDALENA DE KINO SONORA, FRENTE A LA SUBESTACIÓN DE LA COMISIÓN FEDERAL DE ELECTRICIDAD", "pos": [30.625035127784, -110.95232833203], "tipo": "Contigua 02"}, {"presidente": "CRISTAL IRIANA GUZMAN QUEVEDO", "secretario1": "ZAIRA GRISELLE ESPINOZA RUVALCABA", "secretario2": "ANGEL ALBERTO MARTINEZ ARRIOLA", "escrutador1": "LUZ DEL CARMEN GUERLACH BARRERA", "escrutador2": "JESUS EMMANUEL BARRERA PALAFOX", "escrutador3": "YADIRA MARIBEL FUENTES REYES", "suplente1": "JUAN DIEGO MORALES GORTAREZ", "suplente2": "CARMEN MERCEDES CASTRO LEYVA", "suplente3": "MERCEDES PORFIRIA ALVAREZ LEYVA", "direccion": "CENTRO DE ATENCIÓN MULTIPLE, CALLE AGUSTÍN DE ITURBIDE ENTRE SANTIAGO IGLESIAS Y ANTONIA GARCÍA COLONIA LOMAS DE KINO CÓDIGO POSTAL 84160 MAGDALENA DE KINO SONORA, FRENTE A LA SUBESTACIÓN DE LA COMISIÓN FEDERAL DE ELECTRICIDAD", "pos": [30.625035127784, -110.95232833203], "tipo": "Contigua 03"}]}, "geometry": {"type": "Polygon", "coordinates": [[[-110.9534458, 30.6271511], [-110.9539455, 30.6272275], [-110.9542162, 30.627269], [-110.9545067, 30.6272639], [-110.9547971, 30.6272589], [-110.9548815, 30.6273104], [-110.9549118, 30.6273289], [-110.9554481, 30.6276561], [-110.9555202, 30.6277], [-110.9555786, 30.6277506], [-110.9559661, 30.6280859], [-110.9560318, 30.6280327], [-110.9563989, 30.6277354], [-110.9556408, 30.6268839], [-110.9551976, 30.6264149], [-110.9546886, 30.6258763], [-110.9549887, 30.6256008], [-110.9552945, 30.62532], [-110.9557471, 30.6249044], [-110.9559042, 30.6247601], [-110.9561575, 30.6245275], [-110.9565326, 30.6241831], [-110.9574644, 30.6233275], [-110.9581335, 30.622713], [-110.9573122, 30.6218392], [-110.9567501, 30.6212412], [-110.9566, 30.6210809], [-110.9560703, 30.6205114], [-110.9558945, 30.6203219], [-110.9556664, 30.6200761], [-110.955457, 30.6198506], [-110.9551417, 30.6195109], [-110.9544932, 30.618812], [-110.9542311, 30.6185297], [-110.9536895, 30.6179461], [-110.953353, 30.6175835], [-110.9529549, 30.6171546], [-110.9524756, 30.6166029], [-110.9515564, 30.6155446], [-110.9492132, 30.6179912], [-110.9462496, 30.6216901], [-110.9452275, 30.6230047], [-110.9474312, 30.6250066], [-110.9475795, 30.6249967], [-110.9480226, 30.6249821], [-110.948231, 30.6249088], [-110.9484598, 30.6250015], [-110.9489386, 30.6251956], [-110.949565, 30.6254661], [-110.949771, 30.625555], [-110.9502731, 30.6257032], [-110.9507972, 30.6258584], [-110.9515522, 30.6260824], [-110.9518085, 30.6261536], [-110.9521787, 30.6262822], [-110.9531045, 30.6270304], [-110.9532085, 30.6271148], [-110.9533105, 30.6271304], [-110.9534458, 30.6271511]]]}}