{"type": "Feature", "properties": {"Sección": 505, "DEL_ROM": "VI", "Tipo": "Urbana", "DEF": 5, "DEL": 6, "Municipio ID": 49, "Municipio": "Hermosillo", "Lista Nominal": 1228, "Casillas": [{"presidente": "JOEL ENRIQUE ESPEJEL BLANCO", "secretario1": "JOSE ANTONIO MUÑOZ CAÑEZ", "secretario2": "EDUARDO MARIO ARMADA DOBARGANES", "escrutador1": "MARIA GABRIELA DINGFELDER PRIEGO", "escrutador2": "NORMA ALICIA FELIX GRACIA", "escrutador3": "BRENDA FABIOLA GRIJALVA FUENTES", "suplente1": "ANA SOFIA OCHOA SAENZ", "suplente2": "IVANNA CAROLINA GALLEGOS ORTEGA", "suplente3": "DANIEL ARTURO ENRIQUEZ ARVIZU", "direccion": "COLEGIO MUÑOZ, LOS ARCOS, AVENIDA JUAN DE UGARTE, COLONIA LOS ARCOS, HERMOSILLO, 83250, HERMOSILLO, SONORA., FRENTE A PAPELERÍA Y REGALOS CHAMI'S. ENTRE CALLE FRAY BERNARDINO DE SAHAGÚN Y CALLE OLIVARES.", "pos": [29.0790896, -110.9767533], "tipo": "Básica 01"}, {"presidente": "LUIS LEOPOLDO GUEVARA AGUIRRE", "secretario1": "ELSA LORENA ABITIA DUARTE", "secretario2": "EDGAR DIAZ CARRASCO", "escrutador1": "ARTURO DUARTE FEDERICO", "escrutador2": "GABRIELA FIGUEROA SANCHEZ", "escrutador3": "ANNABELLA MONREAL GONZALEZ", "suplente1": "CARLOS EDUARDO FLORES NAVARRO", "suplente2": "BEATRIZ JIMENEZ CANALE", "suplente3": "JORGE ALEJANDRO ENRIQUEZ ARVIZU", "direccion": "COLEGIO MUÑOZ, LOS ARCOS, AVENIDA JUAN DE UGARTE, COLONIA LOS ARCOS, HERMOSILLO, 83250, HERMOSILLO, SONORA., FRENTE A PAPELERÍA Y REGALOS CHAMI'S. ENTRE CALLE FRAY BERNARDINO DE SAHAGÚN Y CALLE OLIVARES.", "pos": [29.0790896, -110.9767533], "tipo": "Contigua 01"}]}, "geometry": {"type": "Polygon", "coordinates": [[[-110.976639, 29.0828806], [-110.9766446, 29.0828362], [-110.9766498, 29.0827942], [-110.9766676, 29.0826519], [-110.9766801, 29.0825516], [-110.9766853, 29.0825104], [-110.9767688, 29.0819824], [-110.9768479, 29.0814822], [-110.9768631, 29.0813856], [-110.9769409, 29.0809972], [-110.9769484, 29.08087], [-110.9769591, 29.0806873], [-110.9769709, 29.0804869], [-110.976984, 29.0802628], [-110.9770254, 29.0795582], [-110.977034, 29.0794108], [-110.9770439, 29.0792597], [-110.9770168, 29.078927], [-110.977007, 29.0788031], [-110.97681, 29.0784723], [-110.9773897, 29.0781889], [-110.9769296, 29.0781067], [-110.9765898, 29.0779599], [-110.9764228, 29.0779092], [-110.9756606, 29.077875], [-110.9751232, 29.0778509], [-110.9745982, 29.0778273], [-110.9740853, 29.0778042], [-110.9735708, 29.0777811], [-110.9730843, 29.0777592], [-110.9726038, 29.0777376], [-110.9720942, 29.0777147], [-110.9717859, 29.0777009], [-110.9709276, 29.0776045], [-110.9709719, 29.0778678], [-110.9710563, 29.0783704], [-110.9711774, 29.0790908], [-110.9712862, 29.0797388], [-110.9713713, 29.0802453], [-110.9714624, 29.0807875], [-110.9714823, 29.080796], [-110.9716871, 29.0808837], [-110.9717681, 29.0814972], [-110.9741548, 29.0820789], [-110.9759381, 29.0826519], [-110.976639, 29.0828806]]]}}