{"type": "Feature", "properties": {"Sección": 703, "DEL_ROM": "I", "Tipo": "Urbana", "DEF": 1, "DEL": 1, "Municipio ID": 55, "Municipio": "San Luis Río Colorado", "Lista Nominal": 1579, "Casillas": [{"presidente": "MARIO ALEJANDRO GARIBALDI VAZQUEZ", "secretario1": "ADRIANA ISABEL CHABOLLA LUA", "secretario2": "GILBERTO HERNANDEZ BELMONTES", "escrutador1": "CRISTOBAL SARIÑANA LOPEZ", "escrutador2": "FELICIANA ROSARIO LEON GUTIERREZ", "escrutador3": "LETICIA ORDAZ AGUAYO", "suplente1": "MARTA ANGULO LOPEZ", "suplente2": "LILIAN MICHELLE DUARTE LEON", "suplente3": "MARTIN ISBAL MONGE VALENZUELA", "direccion": "JARDÍN DE NIÑOS MÉXICO, CALLE YUCATÁN ENTRE CALLEJÓN PLUTARCO ELÍAS CALLES Y AVENIDA EMILIO PORTES GIL, COLONIA INDUSTRIAL, CÓDIGO POSTAL 83430, SAN LUIS RÍO COLORADO, SONORA, A 100 METROS DE PARQUE DEPORTIVO 30 40", "pos": [32.4594432092, -114.80402460719], "tipo": "Básica 01"}, {"presidente": "ANA LUCIA AVILA RODRIGUEZ", "secretario1": "ALAN CORTES PAEZ", "secretario2": "OTTO RENE TERRAZAS PEREZ", "escrutador1": "ANA LUISA CALDERON SANCHEZ", "escrutador2": "EDNA ELIZABETH MADRILES ROMERO", "escrutador3": "EVA LUZ PAEZ PACHECO", "suplente1": "FELIPE CANO PLASCENCIA", "suplente2": "CARLOS ESTEBAN GUTIERREZ CARLIN", "suplente3": "CLAUDIA DILUVINA RAMIREZ CORDOVA", "direccion": "JARDÍN DE NIÑOS MÉXICO, CALLE YUCATÁN ENTRE CALLEJÓN PLUTARCO ELÍAS CALLES Y AVENIDA EMILIO PORTES GIL, COLONIA INDUSTRIAL, CÓDIGO POSTAL 83430, SAN LUIS RÍO COLORADO, SONORA, A 100 METROS DE PARQUE DEPORTIVO 30 40", "pos": [32.4594432092, -114.80402460719], "tipo": "Contigua 01"}, {"presidente": "ATENAS BIRIDIANA CALDERON LUGO", "secretario1": "MATIAS CUARAO CAMPOVERDE", "secretario2": "DANIELA CARRILLO FERNANDEZ", "escrutador1": "JESUS ALEJANDRO GARCIA GONZALEZ", "escrutador2": "JAVIER DIEGO MONGE VALENZUELA", "escrutador3": "ALEJANDRO LOPEZ ASSMAR", "suplente1": "JOSE ALBERTO CRUZ ZAVALA", "suplente2": "MIRIAN LOPEZ AGUIRRE", "suplente3": "MIRNA ALICIA JIMENEZ BOJORQUEZ", "direccion": "JARDÍN DE NIÑOS MÉXICO, CALLE YUCATÁN ENTRE CALLEJÓN PLUTARCO ELÍAS CALLES Y AVENIDA EMILIO PORTES GIL, COLONIA INDUSTRIAL, CÓDIGO POSTAL 83430, SAN LUIS RÍO COLORADO, SONORA, A 100 METROS DE PARQUE DEPORTIVO 30 40", "pos": [32.4594432092, -114.80402460719], "tipo": "Contigua 02"}]}, "geometry": {"type": "Polygon", "coordinates": [[[-114.8150965, 32.4609799], [-114.8153079, 32.460452], [-114.8155366, 32.4598811], [-114.8157563, 32.4593325], [-114.8159866, 32.4587576], [-114.8172852, 32.4591572], [-114.8175136, 32.4585786], [-114.8177413, 32.4580018], [-114.8164634, 32.4576325], [-114.8151267, 32.4572462], [-114.8138203, 32.4568686], [-114.8124087, 32.4564605], [-114.811085, 32.4560779], [-114.8097668, 32.4556969], [-114.8084573, 32.4553183], [-114.8071623, 32.454944], [-114.8058469, 32.4545637], [-114.8045418, 32.4541824], [-114.8045128, 32.4542603], [-114.8043036, 32.4547606], [-114.8040815, 32.4552919], [-114.8040323, 32.4554095], [-114.8036106, 32.456418], [-114.8033794, 32.4569709], [-114.8031731, 32.4574656], [-114.8030398, 32.4577946], [-114.8028525, 32.4582565], [-114.802649, 32.4587586], [-114.8024061, 32.4593579], [-114.8021782, 32.4599201], [-114.8021389, 32.4600171], [-114.8019648, 32.4604463], [-114.8018827, 32.4606489], [-114.8017242, 32.46104], [-114.8016321, 32.4612672], [-114.8014946, 32.4616062], [-114.8013726, 32.4619073], [-114.801274, 32.46215], [-114.8010516, 32.4626979], [-114.800866, 32.4631546], [-114.8018642, 32.4630226], [-114.8032305, 32.4628419], [-114.8045978, 32.462661], [-114.8059812, 32.462478], [-114.8058666, 32.4618901], [-114.8057544, 32.4613149], [-114.8071175, 32.4611348], [-114.8072251, 32.4617085], [-114.8073348, 32.4622942], [-114.8086975, 32.4621162], [-114.8100865, 32.4619347], [-114.8102507, 32.4620243], [-114.8104341, 32.4615865], [-114.8105711, 32.4612593], [-114.8106019, 32.4611858], [-114.8107812, 32.4607576], [-114.8108364, 32.4606258], [-114.8109602, 32.4603303], [-114.8110966, 32.4600044], [-114.8111761, 32.4598145], [-114.8123326, 32.4601583], [-114.8124683, 32.4601987], [-114.8136874, 32.4605611], [-114.8137616, 32.4605831], [-114.8150965, 32.4609799]]]}}