{"type": "Feature", "properties": {"Sección": 769, "DEL_ROM": "XIV", "Tipo": "Urbana", "DEF": 4, "DEL": 14, "Municipio ID": 58, "Municipio": "Bácum", "Lista Nominal": 1182, "Casillas": [{"presidente": "MARIELENA CAMARENA MORENO", "secretario1": "SANDRA JUDITH LOPEZ HUMO", "secretario2": "AMERICA SELENE LOPEZ MENDIVIL", "escrutador1": "JESUS DAVID MARES POLANCO", "escrutador2": "HANNIA MARIA ESQUER GOMEZ", "escrutador3": "ALMA CECILIA DOMINGUEZ MURILLO", "suplente1": "ERIKA SAIDE GARCIA CASTELLANOS", "suplente2": "SANTA AIDEE FINO QUIJADA", "suplente3": "LUIS ANGEL MARES DOMINGUEZ", "direccion": "LOCAL DE EVENTOS , SANTA MARÍA DE GUADALUPE ENTRE CALLES 9 Y SAMUEL OCAÑA GARCÍA, NÚMERO 18, COLONIA FÉLIX B. GARCÍA, FRANCISCO JAVIER MINA, 85270, BÁCUM, SONORA, AL COSTADO DE PURIFICADORA AGUA PURA SANTA MÓNICA", "pos": [27.458712898672, -110.11712802531], "tipo": "Básica 01"}, {"presidente": "AMERICA ESTHEROLIVIA COTA RAMIREZ", "secretario1": "FRANCISCO JAVIER BARRERAS CEBREROS", "secretario2": "GUSTAVO ADOLFO MARES DOMINGUEZ", "escrutador1": "ITZEL GUADALUPE CECEÑA QUIJADA", "escrutador2": "JESUS IVAN CASTELLANOS LOPEZ", "escrutador3": "ROSA MARIA FRAGA PALOMARES", "suplente1": "HERLINDA ESQUER ALVAREZ", "suplente2": "ALEJANDRO GARCIA MONTES", "suplente3": "HERIBERTO LOPEZ GOMEZ", "direccion": "LOCAL DE EVENTOS , SANTA MARÍA DE GUADALUPE ENTRE CALLES 9 Y SAMUEL OCAÑA GARCÍA, NÚMERO 18, COLONIA FÉLIX B. GARCÍA, FRANCISCO JAVIER MINA, 85270, BÁCUM, SONORA, AL COSTADO DE PURIFICADORA AGUA PURA SANTA MÓNICA", "pos": [27.458712898672, -110.11712802531], "tipo": "Contigua 01"}]}, "geometry": {"type": "Polygon", "coordinates": [[[-110.1147276, 27.4576111], [-110.117176, 27.4576055], [-110.1171774, 27.4572275], [-110.1171788, 27.456839], [-110.1171802, 27.456461], [-110.1171817, 27.4560305], [-110.1171832, 27.4556211], [-110.1171848, 27.4551768], [-110.1146784, 27.4551537], [-110.1143913, 27.455151], [-110.1128259, 27.4551366], [-110.1106362, 27.4551164], [-110.1106364, 27.4556318], [-110.1106366, 27.4560518], [-110.1106367, 27.4564193], [-110.1106368, 27.4567974], [-110.110637, 27.4571885], [-110.1106372, 27.4576202], [-110.1128353, 27.4576153], [-110.1147276, 27.4576111]]]}}