{"type": "Feature", "properties": {"Sección": 1502, "DEL_ROM": "XI", "Tipo": "Urbana", "DEF": 3, "DEL": 11, "Municipio ID": 49, "Municipio": "Hermosillo", "Lista Nominal": 334, "Casillas": [{"presidente": "AARON CORDOVA SUAREZ", "secretario1": "PATRICIA CAMACHO CEBREROS", "secretario2": "FLOR ARLENE CEJUDO RAMOS", "escrutador1": "MARIANA FRANCO TANORI", "escrutador2": "PAUL ADAN ALATORRE TREVIÑO", "escrutador3": "ERIKA MAYTE BARRAGAN CONTRERAS", "suplente1": "AARON FERNANDO DUARTE MACIAS", "suplente2": "MARIA DE JESUS FIERROS LOPEZ", "suplente3": "JESUS MANUEL ACOSTA GARCIA", "direccion": "ENTRADA POR BOULEVARD AGUSTIN GOMEZ DEL CAMPO, CERRADA LA CIMA 21 FRACCIONAMIENTO CASA BONITA HERMOSILLO 83175, CASA COLOR NARANJA", "pos": [29.100157, -111.028315], "tipo": "Básica 01"}]}, "geometry": {"type": "Polygon", "coordinates": [[[-111.027667, 29.0994053], [-111.027807, 29.1001039], [-111.027881, 29.1004968], [-111.0279826, 29.1013295], [-111.0292848, 29.1011369], [-111.0293574, 29.1015423], [-111.0294344, 29.1019278], [-111.0294979, 29.1023312], [-111.0295809, 29.1027331], [-111.0296158, 29.1031419], [-111.0297154, 29.1035393], [-111.029788, 29.1039487], [-111.0298232, 29.1039595], [-111.0302471, 29.1038956], [-111.0293971, 29.0992772], [-111.029372, 29.0991011], [-111.0297076, 29.09904], [-111.0408933, 29.0973984], [-111.0416272, 29.0912225], [-111.0405385, 29.091537], [-111.0395621, 29.0917849], [-111.0369901, 29.092438], [-111.0279412, 29.0947353], [-111.0284331, 29.0962438], [-111.0274186, 29.0975114], [-111.027667, 29.0994053]]]}}