{"type": "Feature", "properties": {"Sección": 1524, "DEL_ROM": "XIII", "Tipo": "Urbana", "DEF": 4, "DEL": 13, "Municipio ID": 61, "Municipio": "Guaymas", "Lista Nominal": 1296, "Casillas": [{"presidente": "YAZMIN AZUCENA CORRALES VALENZUELA", "secretario1": "MONICA ALEJANDRA ARAUJO BOJORQUEZ", "secretario2": "SILVIA EDITH DUARTE RASCON", "escrutador1": "DEBORA GURROLA GALLARDO", "escrutador2": "ANGEL FERNANDO ARVIZU PARTIDA", "escrutador3": "ALEJANDRA SARAHI DOMINGUEZ MEDINA", "suplente1": "DELIA LOERA RAMIREZ", "suplente2": "MARIA GUADALUPE CASAVANTES FLORES", "suplente3": "ARCELIA GUADALUPE ARMENTA GASTELUM", "direccion": "PARQUE PÚBLICO ATARDECERES, AMANECER ENTRE ATARDECERES Y VILLA DEL PUERTO 3, FRACCIONAMIENTO ATARDECERES, 85423, GUAYMAS, SONORA, A UNA CALLE DE LA TIENDA DE ABARROTES ATARDECERES", "pos": [27.9143983, -110.9114034], "tipo": "Básica 01"}, {"presidente": "CARLOS DAVID DAVILA BORBON", "secretario1": "SHEILA VIANEY DOMINGUEZ MEDINA", "secretario2": "EDI LILI GONZALEZ RODRIGUEZ", "escrutador1": "LESLY DANIELA MARTINEZ VALENZUELA", "escrutador2": "ISMAEL CAMPA CASTRO", "escrutador3": "GABRIELA LIZARRAGA SANCHEZ", "suplente1": "SABINO MEJIA RAMIREZ", "suplente2": "SERGIO ALEJANDRO ARAUJO RUELAS", "suplente3": "BRANDON NICOLAS GASTELUM VARGAS", "direccion": "PARQUE PÚBLICO ATARDECERES, AMANECER ENTRE ATARDECERES Y VILLA DEL PUERTO 3, FRACCIONAMIENTO ATARDECERES, 85423, GUAYMAS, SONORA, A UNA CALLE DE LA TIENDA DE ABARROTES ATARDECERES", "pos": [27.9143983, -110.9114034], "tipo": "Contigua 01"}]}, "geometry": {"type": "Polygon", "coordinates": [[[-110.9200357, 27.947664], [-110.9197428, 27.9479003], [-110.919629, 27.9479921], [-110.9192592, 27.9482905], [-110.9185512, 27.9488616], [-110.9173191, 27.9498556], [-110.917182, 27.9499662], [-110.9171085, 27.9500254], [-110.9169358, 27.9501648], [-110.9167857, 27.9503126], [-110.9161979, 27.9508044], [-110.9160668, 27.9509027], [-110.9156405, 27.9512621], [-110.9169434, 27.9518039], [-110.9172089, 27.9519143], [-110.9176845, 27.952107], [-110.9181411, 27.9522961], [-110.9184356, 27.9519391], [-110.918729, 27.9515971], [-110.9188861, 27.951397], [-110.9190393, 27.9511933], [-110.9198762, 27.95019], [-110.9199015, 27.9501597], [-110.9201739, 27.9498269], [-110.9204658, 27.9494956], [-110.9207837, 27.9491543], [-110.9212418, 27.9488403], [-110.9214116, 27.948874], [-110.9217669, 27.9476767], [-110.9218717, 27.9472392], [-110.9203162, 27.9474377], [-110.9200357, 27.947664]]]}}