{"type": "Feature", "properties": {"Sección": 319, "DEL_ROM": "III", "Tipo": "Rural", "DEF": 1, "DEL": 3, "Municipio ID": 46, "Municipio": "Caborca", "Lista Nominal": 4324, "Casillas": [{"presidente": "MARTIN GONZALEZ FONCECA", "secretario1": "RICARDO FLORES ROMAN", "secretario2": "NIDIA BERENICE GUERRERO VERA", "escrutador1": "RENULFO ISAEL BALDERRAMA ZAPIEN", "escrutador2": "MARIA DEL ROSARIO CELAYA FLORES", "escrutador3": "LAURA ISELA GAUNA LOPEZ", "suplente1": "KENIA YAMILETH MARTINEZ ARANDA", "suplente2": "GLORIA GUARDADO MARRON", "suplente3": "RAUL GUERRERO CASTRO", "direccion": "ESCUELA SECUNDARIA TÉCNICA NÚMERO 35 , DOMICILIO CONOCIDO, CALLE PRINCIPAL CARRETERA A PUERTO PEÑASCO, COLONIA LA Y, EJIDO PLUTARCO ELÍAS CALLES, CÓDIGO POSTAL 83600, CABORCA, SONORA, A UN COSTADO DE ESCUELA PRIMARIA UNIDAD FORD NÚMERO 66", "pos": [30.803415083403, -112.7178220353], "tipo": "Básica 01"}, {"presidente": "AMERICA DALAY ESCALANTE QUINTERO", "secretario1": "LUISA FERNANDA GAXIOLA BALLESTEROS", "secretario2": "JOSE IVAN HERNANDEZ HERNANDEZ", "escrutador1": "MARIANA BARRAZA CABRAL", "escrutador2": "JOSE ARMANDO CISNEROS ACOSTA", "escrutador3": "ANGEL ARNULFO GUERRERO MAGALLANES", "suplente1": "BLANCA ESTELA MARTINEZ MENDOZA", "suplente2": "BLANCA ALICIA BAUTISTA HERNANDEZ", "suplente3": "JESUS ARMENTA LUQUE", "direccion": "ESCUELA SECUNDARIA TÉCNICA NÚMERO 35 , DOMICILIO CONOCIDO, CALLE PRINCIPAL CARRETERA A PUERTO PEÑASCO, COLONIA LA Y, EJIDO PLUTARCO ELÍAS CALLES, CÓDIGO POSTAL 83600, CABORCA, SONORA, A UN COSTADO DE ESCUELA PRIMARIA UNIDAD FORD NÚMERO 66", "pos": [30.803415083403, -112.7178220353], "tipo": "Contigua 01"}, {"presidente": "JAVIER NAU ARELLANES ARELLANES", "secretario1": "SARA ALI GONZALEZ RIOS", "secretario2": "BEATRIZ ELENA ARANDA CASTILLO", "escrutador1": "GUSTAVO LORENZO BAUTISTA SANCHEZ", "escrutador2": "PATRICIA DIAZ MERCADO", "escrutador3": "VICTOR JUNES MOSQUEDA", "suplente1": "GABRIELA GASTELUM RODRIGUEZ", "suplente2": "PEDRO FLORES QUEVEDO", "suplente3": "JORGE JACOME MORAN", "direccion": "ESCUELA SECUNDARIA TÉCNICA NÚMERO 35 , DOMICILIO CONOCIDO, CALLE PRINCIPAL CARRETERA A PUERTO PEÑASCO, COLONIA LA Y, EJIDO PLUTARCO ELÍAS CALLES, CÓDIGO POSTAL 83600, CABORCA, SONORA, A UN COSTADO DE ESCUELA PRIMARIA UNIDAD FORD NÚMERO 66", "pos": [30.803415083403, -112.7178220353], "tipo": "Contigua 02"}, {"presidente": "JESUS YOVANE GAONA ESTRADA", "secretario1": "GAEL AMIN JASSO SOTO", "secretario2": "ANA ZUGEY ADAME MORALES", "escrutador1": "MONICA CASTILLO MACIAS", "escrutador2": "CARLOS ENCISO ANGULO", "escrutador3": "ALEJANDRA DENISSE MALDONADO LUNA", "suplente1": "RUBICELA LOPEZ ADAME", "suplente2": "MARIO GARCIA CAMBRON", "suplente3": "ARACELY CASTRO GAUNA", "direccion": "ESCUELA SECUNDARIA TÉCNICA NÚMERO 35 , DOMICILIO CONOCIDO, CALLE PRINCIPAL CARRETERA A PUERTO PEÑASCO, COLONIA LA Y, EJIDO PLUTARCO ELÍAS CALLES, CÓDIGO POSTAL 83600, CABORCA, SONORA, A UN COSTADO DE ESCUELA PRIMARIA UNIDAD FORD NÚMERO 66", "pos": [30.803415083403, -112.7178220353], "tipo": "Contigua 03"}, {"presidente": "CESAR EMANUEL CISNEROS MARTINEZ", "secretario1": "KARINA VANESSA MARTINEZ LIRA", "secretario2": "MARITTZA YESENIA ARREDONDO CONTRERAS", "escrutador1": "DULCE LUCIA CASTRO GARCIA", "escrutador2": "CONSUELO GARCIA RIVERA", "escrutador3": "JESUS CRISTIAN MALDONADO LUNA", "suplente1": "NATIVIDAD FLORES SALAZAR", "suplente2": "ALMA LYDIA BOCANEGRA RIOS", "suplente3": "CELESTINO FLORES MARTINEZ", "direccion": "ESCUELA SECUNDARIA TÉCNICA NÚMERO 35 , DOMICILIO CONOCIDO, CALLE PRINCIPAL CARRETERA A PUERTO PEÑASCO, COLONIA LA Y, EJIDO PLUTARCO ELÍAS CALLES, CÓDIGO POSTAL 83600, CABORCA, SONORA, A UN COSTADO DE ESCUELA PRIMARIA UNIDAD FORD NÚMERO 66", "pos": [30.803415083403, -112.7178220353], "tipo": "Contigua 04"}, {"presidente": "JULIA MIREYA AVILA MARTINEZ", "secretario1": "ROSA LIZZET FLORES OCHOA", "secretario2": "FRIDA SOFIA AVILA MARTINEZ", "escrutador1": "JAIME JARET CASILLAS OLOÑO", "escrutador2": "FRANCISCA GONZALEZ NORIS", "escrutador3": "GERMAN GONZALEZ NORIZ", "suplente1": "JOSE FELIPE ALVARADO CRUZ", "suplente2": "SERGIO HERNANDEZ MARTINEZ", "suplente3": "MARIA DEL ROSARIO GONZALEZ MONTIJO", "direccion": "ESCUELA PRIMARIA FEDERAL SALVADOR ALVARADO, DOMICILIO CONOCIDO, EJIDO SANTA EDUWIGES, CÓDIGO POSTAL 83600, CABORCA, SONORA, CONTRA ESQUINA JARDÍN DE NIÑOS GIRASOLES", "pos": [30.76947874863, -112.52373377647], "tipo": "Extraordinaria 01"}]}, "geometry": {"type": "Polygon", "coordinates": [[[-112.711223, 30.831947], [-112.7123676, 30.820852], [-112.7239281, 30.821222], [-112.7329889, 30.8147414], [-112.7383868, 30.81088], [-112.7399985, 30.8006112], [-112.7379548, 30.7935976], [-112.7295337, 30.7646853], [-112.7235192, 30.7624953], [-112.7191692, 30.7610377], [-112.7145714, 30.7606577], [-112.7106052, 30.7592797], [-112.7043102, 30.7532007], [-112.7016091, 30.750075], [-112.6976282, 30.7463791], [-112.6894358, 30.7426306], [-112.6807473, 30.741037], [-112.6743387, 30.7366954], [-112.6716772, 30.7396111], [-112.6744842, 30.7395086], [-112.6725783, 30.7408464], [-112.6698995, 30.7410307], [-112.6674867, 30.7429513], [-112.6674645, 30.7481417], [-112.6658792, 30.7483009], [-112.6635625, 30.7513392], [-112.6620167, 30.7535572], [-112.6599619, 30.7555245], [-112.6588074, 30.7564249], [-112.6572705, 30.7572404], [-112.6554767, 30.7583019], [-112.653944, 30.7584574], [-112.6527964, 30.7582853], [-112.6520377, 30.7572081], [-112.6524324, 30.7553956], [-112.6521869, 30.7539091], [-112.6516872, 30.7522561], [-112.6496685, 30.7486961], [-112.6485351, 30.7463791], [-112.6474013, 30.7441445], [-112.6465183, 30.7425716], [-112.6448807, 30.7393439], [-112.6436249, 30.7362835], [-112.642747, 30.7339681], [-112.6424956, 30.733389], [-112.6418664, 30.732065], [-112.6397177, 30.7289991], [-112.6394647, 30.7286675], [-112.6392161, 30.7276759], [-112.6383329, 30.7261853], [-112.6374492, 30.7247773], [-112.6351587, 30.7238553], [-112.6074637, 30.7249142], [-112.6059094, 30.7282041], [-112.6041156, 30.7292648], [-112.601813, 30.7300746], [-112.6004048, 30.7307253], [-112.6000168, 30.7314653], [-112.5982239, 30.7323609], [-112.5978382, 30.7327709], [-112.5968057, 30.734414], [-112.5956502, 30.7353964], [-112.5951433, 30.734898], [-112.5942513, 30.7347271], [-112.5930964, 30.7356269], [-112.5929605, 30.736781], [-112.5934561, 30.7388468], [-112.5952379, 30.7395187], [-112.596888, 30.7407671], [-112.6002077, 30.7405416], [-112.6013503, 30.7413741], [-112.6027476, 30.7422908], [-112.6029918, 30.7438599], [-112.6037453, 30.7455974], [-112.6033456, 30.7479873], [-112.60269, 30.750458], [-112.6011346, 30.7538303], [-112.6002307, 30.7553093], [-112.5995821, 30.75679], [-112.5973819, 30.7610655], [-112.5966061, 30.7624629], [-112.594288, 30.765335], [-112.5935139, 30.7664849], [-112.5921139, 30.7658981], [-112.5755723, 30.7760996], [-112.5618526, 30.784091], [-112.5500334, 30.7745295], [-112.5482749, 30.7731066], [-112.5107234, 30.7627025], [-112.5095975, 30.7623904], [-112.4904493, 30.7570798], [-112.4473353, 30.74511], [-112.4464588, 30.7563692], [-112.4433245, 30.7556479], [-112.4197553, 30.7502214], [-112.4007916, 30.790273], [-112.358431, 30.7735384], [-112.3013139, 30.7530755], [-112.2832118, 30.7507678], [-112.2445257, 30.7397681], [-112.2438938, 30.7410832], [-112.2428285, 30.7433002], [-112.2424287, 30.7448642], [-112.2419004, 30.7465095], [-112.2410954, 30.7501325], [-112.2402851, 30.7542505], [-112.2388606, 30.756135], [-112.2375699, 30.7574431], [-112.235249, 30.7595666], [-112.2322844, 30.762179], [-112.2316192, 30.7646481], [-112.2769822, 30.7974124], [-112.3287572, 30.8696542], [-112.3406349, 30.9176685], [-112.3470652, 30.9476676], [-112.3519013, 30.9475285], [-112.3560229, 30.9474098], [-112.3569865, 30.9510135], [-112.3570381, 30.9512056], [-112.3578628, 30.9542908], [-112.3573255, 30.95652], [-112.3555117, 30.9584906], [-112.3542039, 30.9609617], [-112.3535557, 30.961701], [-112.3523928, 30.9626842], [-112.3508319, 30.964905], [-112.3496537, 30.9672116], [-112.3489795, 30.9701842], [-112.3483197, 30.971916], [-112.3482948, 30.9740666], [-112.3493919, 30.9787908], [-112.3510086, 30.9828574], [-112.3512397, 30.9850101], [-112.3502867, 30.9899658], [-112.3484463, 30.9941696], [-112.3457003, 30.9991933], [-112.3448922, 31.0026611], [-112.3200149, 31.060527], [-112.3239702, 31.0618008], [-112.3282924, 31.0645666], [-112.3313584, 31.0652538], [-112.3345447, 31.0666037], [-112.3389974, 31.0692048], [-112.3475317, 31.073328], [-112.3503162, 31.0762459], [-112.351449, 31.0779923], [-112.3509166, 31.0797251], [-112.3514033, 31.0819625], [-112.4139149, 31.0813266], [-112.4147525, 31.0813178], [-112.4155902, 31.0813091], [-112.4039661, 31.0549149], [-112.4106159, 31.0557933], [-112.4181775, 31.0552719], [-112.4233158, 31.0538219], [-112.4306183, 31.0535461], [-112.4362439, 31.0544154], [-112.4442938, 31.0561296], [-112.4519538, 31.0584195], [-112.4534853, 31.058927], [-112.4961166, 31.0476519], [-112.5009814, 31.0477686], [-112.5063592, 31.047806], [-112.5125239, 31.045946], [-112.5175328, 31.0444087], [-112.5221551, 31.0431168], [-112.5257617, 31.0409079], [-112.5303908, 31.0388712], [-112.5365489, 31.0375891], [-112.5411666, 31.0367101], [-112.5452862, 31.0343387], [-112.5483752, 31.0326221], [-112.5514664, 31.0306572], [-112.5533968, 31.0295946], [-112.5567399, 31.0280449], [-112.5590488, 31.0275637], [-112.5614958, 31.0260081], [-112.5602311, 31.0243455], [-112.5586095, 31.0197855], [-112.557217, 31.0181221], [-112.5564676, 31.016132], [-112.5552055, 31.0142213], [-112.5543274, 31.0123131], [-112.5528071, 31.0106487], [-112.552697, 31.0087455], [-112.5528499, 31.0060996], [-112.5532549, 31.0038689], [-112.5554438, 31.0024771], [-112.5571223, 31.0009165], [-112.5582834, 30.9999315], [-112.5597097, 30.9979557], [-112.5613942, 30.9957333], [-112.5628143, 30.9944191], [-112.5652757, 30.9912092], [-112.5664496, 30.988818], [-112.5673538, 30.987914], [-112.5690334, 30.9861878], [-112.5700723, 30.9845402], [-112.5723923, 30.9827354], [-112.5775332, 30.9802869], [-112.578821, 30.9793853], [-112.58152, 30.9780791], [-112.5831999, 30.97627], [-112.58501, 30.9742136], [-112.5861802, 30.9721531], [-112.5855601, 30.9699986], [-112.5855751, 30.9683444], [-112.585454, 30.9675992], [-112.5853441, 30.9656133], [-112.5853674, 30.9630493], [-112.584493, 30.9607277], [-112.584247, 30.9596508], [-112.5832395, 30.9579073], [-112.5824878, 30.9561655], [-112.5819958, 30.9540118], [-112.5812502, 30.9516082], [-112.5802429, 30.9498648], [-112.5791731, 30.9479555], [-112.5781033, 30.9460461], [-112.5763271, 30.9444631], [-112.5746858, 30.9421365], [-112.5734936, 30.9405474], [-112.5722855, 30.9388951], [-112.5712732, 30.9376175], [-112.5698846, 30.9357363], [-112.5727334, 30.9319498], [-112.5746684, 30.9301425], [-112.5769856, 30.9285031], [-112.5777698, 30.9278141], [-112.5807244, 30.9252184], [-112.5824004, 30.9237402], [-112.5840575, 30.9218222], [-112.6033041, 30.8995382], [-112.6043433, 30.8971525], [-112.606663, 30.8944452], [-112.6069238, 30.8937044], [-112.6084867, 30.8895071], [-112.6100358, 30.8872896], [-112.6124777, 30.8853254], [-112.6135109, 30.8837646], [-112.6138045, 30.8782391], [-112.6134405, 30.8754319], [-112.6134638, 30.8720496], [-112.6138568, 30.8706496], [-112.6143929, 30.8670232], [-112.6136388, 30.8652033], [-112.6140334, 30.8635559], [-112.6141709, 30.8621543], [-112.6135451, 30.8602528], [-112.612134, 30.8610687], [-112.6097006, 30.861878], [-112.6077841, 30.8618655], [-112.6044632, 30.8616789], [-112.6019072, 30.8617447], [-112.5996056, 30.8619772], [-112.5973064, 30.8618796], [-112.5920607, 30.862835], [-112.5905269, 30.8629073], [-112.5865648, 30.863046], [-112.5845222, 30.8627849], [-112.5823524, 30.8624404], [-112.5794155, 30.8621733], [-112.5768624, 30.8618261], [-112.5750905, 30.8595042], [-112.573315, 30.8576772], [-112.5662315, 30.8479766], [-112.5860648, 30.8390703], [-112.5984177, 30.8370457], [-112.6046509, 30.8360237], [-112.6044771, 30.8345978], [-112.6044378, 30.8342746], [-112.604306, 30.8331934], [-112.6041838, 30.8321899], [-112.6029701, 30.826695], [-112.6028488, 30.8261445], [-112.6008673, 30.8171701], [-112.6002928, 30.814568], [-112.605065, 30.8144435], [-112.6233874, 30.8139638], [-112.623963, 30.8183494], [-112.6265375, 30.8379605], [-112.63803, 30.8413118], [-112.638458, 30.8414366], [-112.6670749, 30.8398788], [-112.6901805, 30.8372317], [-112.6907105, 30.8401248], [-112.6918787, 30.8429305], [-112.693932, 30.8443228], [-112.6965012, 30.8464562], [-112.6976609, 30.8479377], [-112.6969092, 30.8501779], [-112.6942361, 30.8516871], [-112.6911894, 30.8546888], [-112.7037153, 30.8553429], [-112.7054231, 30.8552259], [-112.726703, 30.8537659], [-112.7264165, 30.8492986], [-112.7291742, 30.8397511], [-112.7300342, 30.8367734], [-112.711223, 30.831947]]]}}