{"type": "Feature", "properties": {"Sección": 814, "DEL_ROM": "XVI", "Tipo": "Urbana", "DEF": 6, "DEL": 16, "Municipio ID": 59, "Municipio": "Cajeme", "Lista Nominal": 1074, "Casillas": [{"presidente": "JOANNA PAOLA IBARRA CORDERO", "secretario1": "PATRICIA MONGE KIRK", "secretario2": "ISIS GABRIELA IBARRA CORDERO", "escrutador1": "GABRIELA YAZMIN MENDIVIL RENTERIA", "escrutador2": "JULIO CESAR AMADO VEGA", "escrutador3": "JOSE DANIEL DOMINGUEZ HIDALGO", "suplente1": "ARLETH YERALDINE MONTERO FELIX", "suplente2": "ANA CAROLINA URIAS FREGOSO", "suplente3": "XIMENA PIÑA MONTOYA", "direccion": "BANQUETA, ARIBAIPA NÚMERO 1995, COLONIA INFONAVIT YUKUJIMARI, CIUDAD OBREGÓN, CÓDIGO POSTAL 85120, ESTACIONAMIENTO", "pos": [27.494389362793, -109.95982137483], "tipo": "Básica 01"}, {"presidente": "JORGE LUIS AYALA GASTELUM", "secretario1": "JAIRO DAVID AGUERO MANCINAS", "secretario2": "EVA MARIA CORONADO GUERRERO", "escrutador1": "JANETH MORALES MONTOYA", "escrutador2": "JUANA BARRON VELAZQUEZ", "escrutador3": "LUIS BRANDON GARCIA VIRGEN", "suplente1": "JHONATAN GABRIEL ORTEGA INZUNZA", "suplente2": "PATRICIA VALENZUELA PEREZ", "suplente3": "JESUS EDUARDO VALENZUELA PEREZ", "direccion": "BANQUETA, ARIBAIPA NÚMERO 1995, COLONIA INFONAVIT YUKUJIMARI, CIUDAD OBREGÓN, CÓDIGO POSTAL 85120, ESTACIONAMIENTO", "pos": [27.494389362793, -109.95982137483], "tipo": "Contigua 01"}]}, "geometry": {"type": "Polygon", "coordinates": [[[-109.9610494, 27.4960038], [-109.9610363, 27.4954752], [-109.9610245, 27.4950318], [-109.9610269, 27.4947744], [-109.9610175, 27.4942906], [-109.9610076, 27.4938692], [-109.9599325, 27.4938361], [-109.958616, 27.4938394], [-109.9585682, 27.4938395], [-109.9577513, 27.4938416], [-109.9576413, 27.4938418], [-109.956567, 27.4938445], [-109.9565672, 27.4942829], [-109.9565672, 27.4943594], [-109.9565675, 27.4947277], [-109.9565677, 27.4951034], [-109.9565679, 27.4955091], [-109.9565681, 27.4959572], [-109.9576459, 27.4959879], [-109.9576427, 27.4954849], [-109.9576403, 27.4951151], [-109.9576377, 27.4947221], [-109.9586325, 27.4947211], [-109.9594994, 27.4947201], [-109.959507, 27.4951778], [-109.9596442, 27.4951788], [-109.9596434, 27.4955322], [-109.9596424, 27.4959736], [-109.9610494, 27.4960038]]]}}