{"type": "Feature", "properties": {"Sección": 1475, "DEL_ROM": "VIII", "Tipo": "Urbana", "DEF": 3, "DEL": 8, "Municipio ID": 49, "Municipio": "Hermosillo", "Lista Nominal": 213, "Casillas": [{"presidente": "RAMIRO ALBERTO ARMENTA JAIME", "secretario1": "PAULO SERGIO ALDAY PROVENCIO", "secretario2": "YEDITH AURORA CASTRO VALTIERRA", "escrutador1": "JESUS CORTES ZAVALA", "escrutador2": "MARIA DEL CARMEN GORTAREZ ESPINOZA", "escrutador3": "MARIA ISABEL ACUÑA CRUZ", "suplente1": "MARIA ELENA ANDRADE ESTRADA", "suplente2": "MARIA ISABEL BRAUN CORELLA", "suplente3": "LUZ IMELDA CORONADO GAXIOLA", "direccion": "ENTRADA POR BOULEVARD PASEO REYES CATÓLICOS, CERRADA NORMANDIA FRACCIONAMIENTO PUERTA REAL 83177 HERMOSILLO SONORA , AREA ABIERTA", "pos": [29.118071210948, -111.03734657732], "tipo": "Básica 01"}]}, "geometry": {"type": "Polygon", "coordinates": [[[-111.0390867, 29.116305], [-111.0371174, 29.116569], [-111.0371968, 29.1169346], [-111.0372847, 29.1173129], [-111.0373347, 29.1177296], [-111.0374769, 29.1181302], [-111.0391322, 29.1178788], [-111.0392556, 29.1182772], [-111.039284, 29.1184706], [-111.0393392, 29.1184619], [-111.0395287, 29.118432], [-111.039578, 29.1184243], [-111.0395272, 29.1181896], [-111.0394298, 29.11774], [-111.0393377, 29.1173152], [-111.0392872, 29.1170822], [-111.0390867, 29.116305]]]}}