{"type": "Feature", "properties": {"Sección": 1520, "DEL_ROM": "XIII", "Tipo": "Urbana", "DEF": 4, "DEL": 13, "Municipio ID": 61, "Municipio": "Guaymas", "Lista Nominal": 830, "Casillas": [{"presidente": "OSCAR MAURICIO ELIZARRARAS FARIAS", "secretario1": "JANETH GUADALUPE GAONA ZALDAÑA", "secretario2": "KAREN LINETH GALINDO VALENZUELA", "escrutador1": "ERIKA LIZETH BAÑUELOS LOPEZ", "escrutador2": "ENRIQUE CRUZ MARTINEZ", "escrutador3": "MARIA DEL SOCORRO AMAYA GONZALEZ", "suplente1": "MARIA DE LOS ANGELES GONZALEZ YESCAS", "suplente2": "MARIA DE LOURDES CUADRAS ROSAS", "suplente3": "ALONDRA RENE LAGARDA PEREZ", "direccion": "JARDÍN DE NIÑOS ISIDRO FABELA ALFARO, CERRADA VALLE BONITO ENTRE INTERIOR NORTE Y CERRADA VALLE BONITO, 176, FRACCIONAMIENTO VALLE BONITO, 85423, GUAYMAS, SONORA, A UNA CALLE DEL PANTEÓN MUNICIPAL", "pos": [27.954298556529, -110.91312218479], "tipo": "Básica 01"}, {"presidente": "HORACIO OCTAVIO GARCIA LUNA", "secretario1": "YESSICA GUADALUPE JUAREZ MAULAS", "secretario2": "NOHEMI ARMENTA CASTILLO", "escrutador1": "THALIA INES BELTRAN ARELLANES", "escrutador2": "MARIA INES JIMENEZ NUÑEZ", "escrutador3": "JESUS GARIBAY RIVERA", "suplente1": "ROSA BEATRIZ LAGARDA PEREZ", "suplente2": "JUAN LUIS LOPEZ CERVANTES", "suplente3": "RUBEN ACOSTA MERAZ", "direccion": "JARDÍN DE NIÑOS ISIDRO FABELA ALFARO, CERRADA VALLE BONITO ENTRE INTERIOR NORTE Y CERRADA VALLE BONITO, 176, FRACCIONAMIENTO VALLE BONITO, 85423, GUAYMAS, SONORA, A UNA CALLE DEL PANTEÓN MUNICIPAL", "pos": [27.954298556529, -110.91312218479], "tipo": "Contigua 01"}]}, "geometry": {"type": "Polygon", "coordinates": [[[-110.908191, 27.9546232], [-110.9079972, 27.9548302], [-110.9078696, 27.9550144], [-110.908761, 27.9564184], [-110.9104701, 27.9571323], [-110.9113156, 27.9555828], [-110.9114678, 27.955644], [-110.9115054, 27.9556644], [-110.911489, 27.9556988], [-110.9114085, 27.9558683], [-110.9109648, 27.9567423], [-110.9114085, 27.9569226], [-110.9118552, 27.9571032], [-110.912254, 27.957273], [-110.912696, 27.9574612], [-110.9132649, 27.9577044], [-110.9135927, 27.9578446], [-110.9144094, 27.9568539], [-110.9149828, 27.9561583], [-110.9156365, 27.9553654], [-110.9157179, 27.9552634], [-110.9152473, 27.9550703], [-110.9146577, 27.9548283], [-110.9144385, 27.9547384], [-110.9141804, 27.9546292], [-110.913207, 27.9542249], [-110.9126094, 27.9539766], [-110.9123035, 27.9538372], [-110.91195, 27.9536939], [-110.9107975, 27.9532173], [-110.9099347, 27.9528269], [-110.9098438, 27.9529355], [-110.9066522, 27.9515261], [-110.9058012, 27.9529442], [-110.9066974, 27.9534416], [-110.908191, 27.9546232]]]}}