{"type": "Feature", "properties": {"Sección": 430, "DEL_ROM": "IX", "Tipo": "Urbana", "DEF": 3, "DEL": 9, "Municipio ID": 49, "Municipio": "Hermosillo", "Lista Nominal": 1967, "Casillas": [{"presidente": "ABIGAIL CORDOVA CORONADO", "secretario1": "LEONOR FLORES BADUQUI", "secretario2": "ALAN GILBERTO CARLON MEZA", "escrutador1": "JUAN MIGUEL BAEZ ARREDONDO", "escrutador2": "MARIA ELIZABETH MARGARITA SOTO TREJO", "escrutador3": "LILIAN SUSANA ZUÑIGA CASTRO", "suplente1": "OLGA LIDIA CASTRO ESTRADA", "suplente2": "CLAUDIA FIGUEROA CORONADO", "suplente3": "EDGAR ALBERTO PACHECO HUICOZA", "direccion": "ENTRE CALLE HERMANOS TALAMANTES Y CALLE CARLOS BALDERRAMA , AVENIDA LUIS ORCÍ 1297 COLONIA SAHUARO 83178 HERMOSILLO SONORA , FRENTE A TORTILLERÍA", "pos": [29.1056672, -111.010323], "tipo": "Básica 01"}, {"presidente": "ARACELY GUTIERREZ GARCIA", "secretario1": "ROSA DALIA GASTELUM MENDIVIL", "secretario2": "RAFAEL JOSE FAVA CASTILLO", "escrutador1": "JOSE LUIS BOJORQUEZ ZAMORA", "escrutador2": "MERCEDES TERAN BUSTILLOS", "escrutador3": "KARLA LIZETH ARVAYO GOMEZ", "suplente1": "EDUARDO ELIZALDE GONZALEZ", "suplente2": "MIGUEL GOMEZ SANDOVAL", "suplente3": "LUISA MARIA ROMERO VALENZUELA", "direccion": "ENTRE CALLE HERMANOS TALAMANTES Y CALLE CARLOS BALDERRAMA , AVENIDA LUIS ORCÍ 1297 COLONIA SAHUARO 83178 HERMOSILLO SONORA , FRENTE A TORTILLERÍA", "pos": [29.1056672, -111.010323], "tipo": "Contigua 01"}, {"presidente": "MARILIK MORENO PEREZ", "secretario1": "IRVIN MANUEL VARGAS BOJORQUEZ", "secretario2": "KARLA FELICITA AMPARANO LOPEZ", "escrutador1": "JESUS MANUEL SOTO TREJO", "escrutador2": "DIANA ELIZABETH TORRES BORJA", "escrutador3": "JOHANA EVANGELINA BARRERA LOPEZ", "suplente1": "RAMONA ESCARREGA URIAS", "suplente2": "CLAUDIA PATRICIA GRANILLO CORRALES", "suplente3": "MARTIN VASQUEZ VALENZUELA", "direccion": "ENTRE CALLE HERMANOS TALAMANTES Y CALLE CARLOS BALDERRAMA , AVENIDA LUIS ORCÍ 1297 COLONIA SAHUARO 83178 HERMOSILLO SONORA , FRENTE A TORTILLERÍA", "pos": [29.1056672, -111.010323], "tipo": "Contigua 02"}]}, "geometry": {"type": "Polygon", "coordinates": [[[-111.0229532, 29.1052668], [-111.0228697, 29.1037684], [-111.0202256, 29.1037871], [-111.0201496, 29.1035022], [-111.0201073, 29.1033436], [-111.019838, 29.1033411], [-111.018896, 29.1033323], [-111.0187863, 29.1033313], [-111.0182746, 29.1033265], [-111.0170882, 29.1033295], [-111.0160624, 29.1033321], [-111.0159489, 29.1033324], [-111.0147972, 29.1033353], [-111.013645, 29.1033381], [-111.0125005, 29.103341], [-111.011325, 29.1033439], [-111.010186, 29.1033467], [-111.0101874, 29.1038207], [-111.0101885, 29.1042224], [-111.0101897, 29.1046579], [-111.0101909, 29.1050692], [-111.0101922, 29.1055274], [-111.0101934, 29.1059668], [-111.0101946, 29.1063799], [-111.0113334, 29.1063711], [-111.0124971, 29.1063622], [-111.0124948, 29.1059526], [-111.0124924, 29.1055333], [-111.0136453, 29.1055261], [-111.0147821, 29.105519], [-111.0159493, 29.1055117], [-111.0171092, 29.1055062], [-111.0182796, 29.1055409], [-111.0190014, 29.1055558], [-111.0206128, 29.105438], [-111.0229532, 29.1052668]]]}}